nb_print/__init__.py
very_nb_print-2.1.dist-info/LICENSE
very_nb_print-2.1.dist-info/METADATA
very_nb_print-2.1.dist-info/WHEEL
very_nb_print-2.1.dist-info/top_level.txt
very_nb_print-2.1.dist-info/RECORD
